pymrz/__init__.py
pymrz/read.py
PyMRZ-0.1.dist-info/LICENSE
PyMRZ-0.1.dist-info/METADATA
PyMRZ-0.1.dist-info/WHEEL
PyMRZ-0.1.dist-info/top_level.txt
PyMRZ-0.1.dist-info/RECORD
