Metadata-Version: 2.1
Name: PyMRZ
Version: 0.1
Summary: Read and Generate Passport Machine Readable Zones (MRZs) with Python
Home-page: https://github.com/MrArobuz/pymrz
Author: Aron Buzinkay
Author-email: UNKNOWN
License: MIT
Platform: UNKNOWN
Classifier: Programming Language :: Python :: 3
Classifier: License :: OSI Approved :: MIT License
Classifier: Operating System :: OS Independent
